tests/__init__.py
tests/conftest.py
tests/constants.py
tests/helpers.py
tests/test_expressions.py
tests/test_formula.py
tests/test_reasoning.py
tests/test_txscript.py
tests/test_txscript_formulas.py
txscript/__init__.py
txscript/annotation.py
txscript/builtins.py
txscript/computed.py
txscript/datapoint.py
txscript/eval.py
txscript/exceptions.py
txscript/fields.py
txscript/flatdata.py
txscript/formula.py
txscript/reasoning.py
txscript/txscript.py
txscript-1.1.0.dist-info/licenses/LICENSE
txscript-1.1.0.dist-info/METADATA
txscript-1.1.0.dist-info/WHEEL
txscript-1.1.0.dist-info/top_level.txt
txscript-1.1.0.dist-info/RECORD
