Metadata-Version: 2.4
Name: txscript
Version: 1.1.0
Summary: Transaction scripts for manipulating business transactions and documents in Rossum platform
Author-email: Petr Baudis <petr.baudis@rossum.ai>
Project-URL: Documentation, https://elis.rossum.ai/api/docs/#rossum-transaction-scripts
Classifier: Programming Language :: Python :: 3
Classifier: License :: OSI Approved :: MIT License
Classifier: Operating System :: OS Independent
Requires-Python: ~=3.8
License-File: LICENSE
Dynamic: license-file
Dynamic: requires-python
